quantizers/__init__.py
quantizers/_version.py
quantizers/stateful_quantizers.py
quantizers/binary/__init__.py
quantizers/binary/_binary_ops.py
quantizers/binary/binary_ops.py
quantizers/binary/binary_ops_np.py
quantizers/fixed_point/__init__.py
quantizers/fixed_point/_fixed_point_ops.py
quantizers/fixed_point/fixed_point_ops.py
quantizers/fixed_point/fixed_point_ops_np.py
quantizers/minifloat/__init__.py
quantizers/minifloat/_float_point_ops.py
quantizers/minifloat/float_point_ops.py
quantizers/minifloat/float_point_ops_np.py
quantizers-1.2.2.dist-info/licenses/LICENSE
quantizers-1.2.2.dist-info/METADATA
quantizers-1.2.2.dist-info/WHEEL
quantizers-1.2.2.dist-info/top_level.txt
quantizers-1.2.2.dist-info/RECORD
