Metadata-Version: 2.4
Name: quantizers
Version: 1.2.2
Author-email: Chang Sun <chsun@cern.ch>
License: GNU Lesser General Public License v3 (LGPLv3)
Project-URL: repository, https://github.com/calad0i/quantizers
Keywords: quantization
Classifier: Programming Language :: Python :: 3
Classifier: Operating System :: OS Independent
Classifier: License :: OSI Approved :: GNU Lesser General Public License v3 (LGPLv3)
Classifier: Development Status :: 5 - Production/Stable
Requires-Python: >=3.10
License-File: LICENSE
Provides-Extra: dependencies
Requires-Dist: numpy; extra == "dependencies"
Provides-Extra: grad
Requires-Dist: keras>=3.10; extra == "grad"
Provides-Extra: test
Requires-Dist: pytest; extra == "test"
Requires-Dist: pytest-cov; extra == "test"
Requires-Dist: pytest-xdist; extra == "test"
Requires-Dist: pytest-env; extra == "test"
Requires-Dist: keras>=3.0; extra == "test"
Requires-Dist: cppyy; extra == "test"
Requires-Dist: jax; extra == "test"
Dynamic: license-file
